README.md
setup.py
Crypro/__init__.py
Crypro/__version__.py
Crypro/app.py
Crypro/decryptoapp.py
Crypro/pct_warnings.py
Crypro/settings.py
Crypro.egg-info/PKG-INFO
Crypro.egg-info/SOURCES.txt
Crypro.egg-info/dependency_links.txt
Crypro.egg-info/top_level.txt
Crypro/Cipher/AES.py
Crypro/Cipher/ARC2.py
Crypro/Cipher/ARC4.py
Crypro/Cipher/Blowfish.py
Crypro/Cipher/CAST.py
Crypro/Cipher/DES.py
Crypro/Cipher/DES3.py
Crypro/Cipher/PKCS1_OAEP.py
Crypro/Cipher/PKCS1_v1_5.py
Crypro/Cipher/XOR.py
Crypro/Cipher/__init__.py
Crypro/Cipher/aesEncrypt.py
Crypro/Cipher/blockalgo.py
Crypro/Hash/HMAC.py
Crypro/Hash/MD2.py
Crypro/Hash/MD4.py
Crypro/Hash/MD5.py
Crypro/Hash/RIPEMD.py
Crypro/Hash/SHA.py
Crypro/Hash/SHA224.py
Crypro/Hash/SHA256.py
Crypro/Hash/SHA384.py
Crypro/Hash/SHA512.py
Crypro/Hash/__init__.py
Crypro/Hash/hashalgo.py
Crypro/Protocol/AllOrNothing.py
Crypro/Protocol/Chaffing.py
Crypro/Protocol/KDF.py
Crypro/Protocol/__init__.py
Crypro/PublicKey/DSA.py
Crypro/PublicKey/ElGamal.py
Crypro/PublicKey/RSA.py
Crypro/PublicKey/_DSA.py
Crypro/PublicKey/_RSA.py
Crypro/PublicKey/__init__.py
Crypro/PublicKey/_slowmath.py
Crypro/PublicKey/pubkey.py
Crypro/Random/_UserFriendlyRNG.py
Crypro/Random/__init__.py
Crypro/Random/random.py
Crypro/Random/Fortuna/FortunaAccumulator.py
Crypro/Random/Fortuna/FortunaGenerator.py
Crypro/Random/Fortuna/SHAd256.py
Crypro/Random/Fortuna/__init__.py
Crypro/Random/OSRNG/__init__.py
Crypro/Random/OSRNG/fallback.py
Crypro/Random/OSRNG/posix.py
Crypro/Random/OSRNG/rng_base.py
Crypro/SelfTest/__init__.py
Crypro/SelfTest/st_common.py
Crypro/SelfTest/Cipher/__init__.py
Crypro/SelfTest/Cipher/common.py
Crypro/SelfTest/Cipher/test_AES.py
Crypro/SelfTest/Cipher/test_ARC2.py
Crypro/SelfTest/Cipher/test_ARC4.py
Crypro/SelfTest/Cipher/test_Blowfish.py
Crypro/SelfTest/Cipher/test_CAST.py
Crypro/SelfTest/Cipher/test_DES.py
Crypro/SelfTest/Cipher/test_DES3.py
Crypro/SelfTest/Cipher/test_XOR.py
Crypro/SelfTest/Cipher/test_pkcs1_15.py
Crypro/SelfTest/Cipher/test_pkcs1_oaep.py
Crypro/SelfTest/Hash/__init__.py
Crypro/SelfTest/Hash/common.py
Crypro/SelfTest/Hash/test_HMAC.py
