Metadata-Version: 2.1
Name: Crypro
Version: 2.0.3
Summary: Simple symmetric GPG file encryption and decryption.
Home-page: https://github.com/BarryYBL/Crypro.git
Author: Barry
Author-email: YBL2652612315@126.com
License: Apache License 2.0
Platform: UNKNOWN
Classifier: License :: OSI Approved :: MIT License
Classifier: Programming Language :: Python
Classifier: Programming Language :: Python :: 3
Classifier: Programming Language :: Python :: 3.6
Classifier: Programming Language :: Python :: Implementation :: CPython
Classifier: Programming Language :: Python :: Implementation :: PyPy
Requires-Python: >=3.5.0
